{
    "bg_edge2": "#090c0d",
    "bg_edge": "#191c1e",
    "bg": "#272a2c",
    "bg_mid": "#404446",
    "bg_mid2": "#5c5f61",
    "fg_edge2": "#edeeff",
    "fg_edge": "#dfdff3",
    "fg": "#d0d0e4",
    "fg_mid": "#b2b2c5",
    "fg_mid2": "#9494a7",
    "red": "#ffa2d2",
    "red_bg": "#65003e",
    "orange": "#ffa68b",
    "orange_bg": "#721b00",
    "yellow": "#ffc758",
    "yellow_bg": "#7c5800",
    "green": "#b7e569",
    "green_bg": "#466100",
    "cyan": "#32f3c5",
    "cyan_bg": "#00785f",
    "azure": "#64e1ff",
    "azure_bg": "#007388",
    "blue": "#8db9ff",
    "blue_bg": "#002777",
    "purple": "#d8abff",
    "purple_bg": "#410067",
    "accent": "#65003e",
    "accent_bg": "#272a2c"
}
